mvstd/__init__.py
mvstd/mvstd.py
mvstd-1.0.4.dist-info/METADATA
mvstd-1.0.4.dist-info/WHEEL
mvstd-1.0.4.dist-info/entry_points.txt
mvstd-1.0.4.dist-info/top_level.txt
mvstd-1.0.4.dist-info/RECORD
