Metadata-Version: 2.1
Name: mvstd
Version: 1.0.4
Summary: Rename files using a standard format
Home-page: https://github.com/jncraton/mvstd
Author: Jon Craton
Author-email: jon@joncraton.com
License: UNKNOWN
Platform: UNKNOWN
Classifier: Programming Language :: Python :: 3
Classifier: License :: OSI Approved :: MIT License
Classifier: Operating System :: OS Independent
Requires-Python: >=3.6
